cov_estimator/__init__.py
cov_estimator/pipeline.py
cov_estimator/nodes/__init__.py
cov_estimator/nodes/abstract_estimator.py
cov_estimator/nodes/estimator.py
cov_estimator/nodes/keras_estimator.py
cov_estimator/nodes/sklearn_estimator.py
cov_estimator/nodes/transformation_node.py
tests/__init__.py
tests/estimator_test.py
tests/transform_test.py
cov_estimator-0.0.1.dist-info/METADATA
cov_estimator-0.0.1.dist-info/WHEEL
cov_estimator-0.0.1.dist-info/top_level.txt
cov_estimator-0.0.1.dist-info/RECORD
