Metadata-Version: 2.1
Name: cov-estimator
Version: 0.0.1
Summary: A small ML serialization software
Home-page: https://github.com/COVID-X/cov-estimator
Author: Levensworth
Author-email: santiago.bassani96@gmail.com
License: UNKNOWN
Platform: UNKNOWN
Classifier: Programming Language :: Python :: 3
Classifier: License :: OSI Approved :: MIT License
Classifier: Operating System :: OS Independent
Requires-Python: >=3.6
